slowloris.py
Slowloris-0.2.6.dist-info/LICENSE
Slowloris-0.2.6.dist-info/METADATA
Slowloris-0.2.6.dist-info/WHEEL
Slowloris-0.2.6.dist-info/entry_points.txt
Slowloris-0.2.6.dist-info/top_level.txt
Slowloris-0.2.6.dist-info/RECORD
